uniqseq/__init__.py
uniqseq/__main__.py
uniqseq/_version.py
uniqseq/buffering.py
uniqseq/cli.py
uniqseq/divergence.py
uniqseq/emission.py
uniqseq/filtering.py
uniqseq/hashing.py
uniqseq/history.py
uniqseq/indexing.py
uniqseq/library.py
uniqseq/matching.py
uniqseq/output.py
uniqseq/preloading.py
uniqseq/processing.py
uniqseq/recording.py
uniqseq/uniqseq.py
uniqseq-0.3.0.dist-info/METADATA
uniqseq-0.3.0.dist-info/WHEEL
uniqseq-0.3.0.dist-info/entry_points.txt
uniqseq-0.3.0.dist-info/licenses/LICENSE
uniqseq-0.3.0.dist-info/RECORD
